hcristian/__init__.py
hcristian/main.py
hcristian-2.0.9.dist-info/METADATA
hcristian-2.0.9.dist-info/WHEEL
hcristian-2.0.9.dist-info/entry_points.txt
hcristian-2.0.9.dist-info/RECORD
