Metadata-Version: 2.1
Name: hcristian
Version: 2.0.9
Summary: Juniper checks
Author: Cristian Bandea
Author-email: cristian.bandea@gmail.com
Requires-Python: >=3.8.1,<3.11
Classifier: Programming Language :: Python :: 3
Classifier: Programming Language :: Python :: 3.9
Classifier: Programming Language :: Python :: 3.10
Requires-Dist: junos-eznc (>=2.6.7,<3.0.0)
